{
  "annotations": { "list": [] },
  "editable": true,
  "fiscalYearStartMonth": 0,
  "graphTooltip": 0,
  "links": [],
  "liveNow": true,
  "panels": [
    {
      "datasource": { "type": "postgres", "uid": "TimescaleDB" },
      "fieldConfig": {
        "defaults": {
          "color": { "mode": "palette-classic" },
          "custom": { "drawStyle": "line", "lineInterpolation": "linear" },
          "unit": "currencyUSD"
        }
      },
      "gridPos": { "h": 12, "w": 24, "x": 0, "y": 0 },
      "id": 1,
      "options": { "legend": { "displayMode": "list", "placement": "bottom" } },
      "targets": [
        {
          "datasource": { "type": "postgres", "uid": "TimescaleDB" },
          "format": "time_series",
          "rawSql": "SELECT $__timeGroupAlias(time, 1s), symbol, avg(price) AS price FROM metrics WHERE $__timeFilter(time) GROUP BY 1, 2 ORDER BY 1",
          "refId": "A"
        }
      ],
      "title": "Crypto Prices Live",
      "type": "timeseries"
    }
  ],
  "refresh": "5s",
  "schemaVersion": 38,
  "style": "dark",
  "tags": [],
  "templating": { "list": [] },
  "time": { "from": "now-5m", "to": "now" },
  "timepicker": {},
  "timezone": "",
  "title": "Massive Event Streamer Dashboard",
  "version": 1
}